{
    "машинка от катышек": {
        "total_stock": 3195,
        "warehouses": 2,
        "details": {
            "Тула": 2710,
            "Коледино": 485
        }
    },
    "ми бенд 9": {
        "total_stock": 298,
        "warehouses": 3,
        "details": {
            "Электросталь": 296,
            "Тула": 1,
            "Котовск": 1
        }
    },
    "ми бенд 7": "Stock info not found",
    "сушилка": {
        "total_stock": 228,
        "warehouses": 2,
        "details": {
            "Коледино": 148,
            "Электросталь": 80
        }
    },
    "гриль": {
        "total_stock": 350,
        "warehouses": 2,
        "details": {
            "Коледино": 349,
            "Алматы Атакент": 1
        }
    },
    "отпар new": {
        "total_stock": 401,
        "warehouses": 1,
        "details": {
            "Электросталь": 401
        }
    },
    "отпар old": {
        "total_stock": 203,
        "warehouses": 3,
        "details": {
            "Электросталь": 201,
            "Казань": 1,
            "Котовск": 1
        }
    },
    "G20 Lite": {
        "total_stock": 51,
        "warehouses": 2,
        "details": {
            "Тула": 47,
            "Коледино": 4
        }
    },
    "G24": {
        "total_stock": 396,
        "warehouses": 2,
        "details": {
            "Электросталь": 395,
            "Котовск": 1
        }
    },
    "X27G": {
        "total_stock": 489,
        "warehouses": 2,
        "details": {
            "Электросталь": 488,
            "Тула": 1
        }
    },
    "X34": {
        "total_stock": 83,
        "warehouses": 1,
        "details": {
            "Электросталь": 83
        }
    },
    "вертушка": {
        "total_stock": 594,
        "warehouses": 2,
        "details": {
            "Коледино": 511,
            "Краснодар (Тихорецкая)": 83
        }
    },
    "увлж 03": {
        "total_stock": 125,
        "warehouses": 1,
        "details": {
            "Электросталь": 125
        }
    },
    "увлж 05": {
        "total_stock": 44,
        "warehouses": 1,
        "details": {
            "Электросталь": 44
        }
    },
    "увлж 06": {
        "total_stock": 220,
        "warehouses": 2,
        "details": {
            "Электросталь": 219,
            "Невинномысск": 1
        }
    },
    "21.45": {
        "total_stock": 47,
        "warehouses": 2,
        "details": {
            "Электросталь": 46,
            "Котовск": 1
        }
    }
}